LCSpy/LoFAR_cat_search.py
LCSpy/__init__.py
LCSpy/cutout_2d.py
LCSpy/download_mosaic.py
LCSpy-0.0.3.dist-info/LICENSE
LCSpy-0.0.3.dist-info/METADATA
LCSpy-0.0.3.dist-info/WHEEL
LCSpy-0.0.3.dist-info/top_level.txt
LCSpy-0.0.3.dist-info/RECORD
